{
    "Patient": {
        "resourceType": "Patient",
        "id": "1aa84ed9-01fb-45b7-b2fe-772fccf48ed3",
        "identifier": [
            {
                "system": "http://satusehat.kemkes.go.id/nik",
                "value": "3276010101010003"
            },
            {
                "system": "https://fhir.kemkes.go.id/id/ihs-number",
                "value": "806039"
            }
        ],
        "active": true,
        "name": [
            {
                "use": "official",
                "text": "dewi santika"
            }
        ],
        "gender": "female",
        "birthDate": "1967",
        "telecom": [
            {
                "system": "phone",
                "value": "+6282234567654"
            }
        ],
        "address": [
            {
                "line": [
                    "jl. imam bonjol no. 78"
                ],
                "city": "surabaya",
                "country": "ID"
            }
        ],
        "meta": {
            "profile": [
                "http://hl7.org/fhir/StructuredDefinition/Patient"
            ]
        }
    },
    "Practitioner": {
        "resourceType": "Practitioner",
        "id": "1aa84ed9-01fb-45b7-b2fe-772fccf48ed3",
        "identifier": [
            {
                "system": "http://satusehat.kemkes.go.id/nik",
                "value": "3173010202020005"
            }
        ],
        "active": true,
        "name": [
            {
                "text": "dr. sumarno hadi"
            }
        ],
        "meta": {
            "profile": [
                "http://hl7.org/fhir/StructuredDefinition/Practitioner"
            ]
        }
    },
    "Condition": {
        "resourceType": "Condition",
        "id": "1aa84ed9-01fb-45b7-b2fe-772fccf48ed3",
        "clinicalStatus": {
            "coding": [
                {
                    "system": "http://terminology.hl7.org/CodeSystem/condition-clinical",
                    "code": "active",
                    "display": "Active"
                }
            ]
        },
        "code": {
            "text": "nyeri punggung, batuk"
        },
        "note": {
            "text": [
                "diberikan obat antihipertensi"
            ]
        },
        "subject": {
            "reference": "Patient/3276010101010003"
        },
        "onsetDateTime": "2023-08-12"
    },
    "Encounter": {
        "resourceType": "Encounter",
        "id": "1aa84ed9-01fb-45b7-b2fe-772fccf48ed3",
        "subject": {
            "reference": "Patient/3276010101010003"
        },
        "period": {
            "start": "2023-08-12"
        },
        "participant": [
            {
                "individual": {
                    "reference": "Referral Doctor/dr. dian"
                }
            }
        ],
        "note": [
            {
                "text": [
                    "direkomendasikan untuk menjaga pola makan dan olahraga"
                ]
            }
        ]
    }
}