{
    "Patient": {
        "resourceType": "Patient",
        "id": "2cb061c2-b5e3-48f6-9ea9-9be3e287306c",
        "identifier": [
            {
                "system": "http://satusehat.kemkes.go.id/nik",
                "value": "3276010101010004"
            },
            {
                "system": "https://fhir.kemkes.go.id/id/ihs-number",
                "value": "406531"
            }
        ],
        "active": true,
        "name": [
            {
                "use": "official",
                "text": "andi suryana"
            }
        ],
        "gender": "female",
        "birthDate": "1943",
        "telecom": [
            {
                "system": "phone",
                "value": "+6281987654321"
            }
        ],
        "address": [
            {
                "line": [
                    "jl. imam bonjol no. 78"
                ],
                "city": "surabaya",
                "country": "ID"
            }
        ],
        "meta": {
            "profile": [
                "http://hl7.org/fhir/StructuredDefinition/Patient"
            ]
        }
    },
    "Practitioner": {
        "resourceType": "Practitioner",
        "id": "2cb061c2-b5e3-48f6-9ea9-9be3e287306c",
        "identifier": [
            {
                "system": "http://satusehat.kemkes.go.id/nik",
                "value": "3173010202020010"
            }
        ],
        "active": true,
        "name": [
            {
                "text": "dr. sumarno hadi"
            }
        ],
        "meta": {
            "profile": [
                "http://hl7.org/fhir/StructuredDefinition/Practitioner"
            ]
        }
    },
    "Condition": {
        "resourceType": "Condition",
        "id": "2cb061c2-b5e3-48f6-9ea9-9be3e287306c",
        "clinicalStatus": {
            "coding": [
                {
                    "system": "http://terminology.hl7.org/CodeSystem/condition-clinical",
                    "code": "active",
                    "display": "Active"
                }
            ]
        },
        "code": {
            "text": "infeksi saluran pernapasan, kelelahan"
        },
        "note": {
            "text": [
                "diberikan antibiotik selama 5 hari"
            ]
        },
        "subject": {
            "reference": "Patient/3276010101010004"
        },
        "onsetDateTime": "2023-07-20"
    },
    "Encounter": {
        "resourceType": "Encounter",
        "id": "2cb061c2-b5e3-48f6-9ea9-9be3e287306c",
        "subject": {
            "reference": "Patient/3276010101010004"
        },
        "period": {
            "start": "2023-07-20"
        },
        "participant": [
            {
                "individual": {
                    "reference": "Referral Doctor/dr. lukman"
                }
            }
        ],
        "note": [
            {
                "text": [
                    "akan dirujuk ke spesialis untuk evaluasi lebih lanjut"
                ]
            }
        ]
    }
}